pyhelpertool/HelperGraphics.py
pyhelpertool/HelperUS.py
pyhelpertool/Helpers.py
pyhelpertool/HelpersAcoustic.py
pyhelpertool/HelpersFiltering.py
pyhelpertool/HelpersIO.py
pyhelpertool/HelpersPlasma.py
pyhelpertool/HelpersSignal.py
pyhelpertool/__init__.py
pyhelpertool-0.22.4.dist-info/LICENSE.md
pyhelpertool-0.22.4.dist-info/METADATA
pyhelpertool-0.22.4.dist-info/WHEEL
pyhelpertool-0.22.4.dist-info/top_level.txt
pyhelpertool-0.22.4.dist-info/RECORD
