Metadata-Version: 2.1
Name: pyhelpertool
Version: 0.22.4
Summary: A collection of helping tools and implementations.
Home-page: https://github.com/hufe/pyhelpertool
Author: Daniel Hufschläger
Author-email: daniel@hufschlaeger.net
License: MIT
Platform: UNKNOWN
